jupyter_exec/__init__.py
jupyter_exec/_version.py
jupyter_exec/handlers.py
jupyter_exec/tests/__init__.py
jupyter_exec/tests/test_handlers.py
jupyter_exec-0.0.3.data/data/etc/jupyter/jupyter_notebook_config.d/jupyter_exec.json
jupyter_exec-0.0.3.data/data/etc/jupyter/jupyter_server_config.d/jupyter_exec.json
jupyter_exec-0.0.3.data/data/share/jupyter/labextensions/@datalayer/jupyter-exec/build_log.json
jupyter_exec-0.0.3.data/data/share/jupyter/labextensions/@datalayer/jupyter-exec/package.json
jupyter_exec-0.0.3.data/data/share/jupyter/labextensions/@datalayer/jupyter-exec/schemas/@datalayer/jupyter-exec/package.json.orig
jupyter_exec-0.0.3.data/data/share/jupyter/labextensions/@datalayer/jupyter-exec/schemas/@datalayer/jupyter-exec/plugin.json
jupyter_exec-0.0.3.data/data/share/jupyter/labextensions/@datalayer/jupyter-exec/static/lib_index_js.df0ab7242dbf32d4e271.js
jupyter_exec-0.0.3.data/data/share/jupyter/labextensions/@datalayer/jupyter-exec/static/lib_index_js.df0ab7242dbf32d4e271.js.map
jupyter_exec-0.0.3.data/data/share/jupyter/labextensions/@datalayer/jupyter-exec/static/node_modules_object-assign_index_js.e2c57204ce0ba95914d0.js
jupyter_exec-0.0.3.data/data/share/jupyter/labextensions/@datalayer/jupyter-exec/static/node_modules_object-assign_index_js.e2c57204ce0ba95914d0.js.map
jupyter_exec-0.0.3.data/data/share/jupyter/labextensions/@datalayer/jupyter-exec/static/remoteEntry.28f290402448f57ddc18.js
jupyter_exec-0.0.3.data/data/share/jupyter/labextensions/@datalayer/jupyter-exec/static/remoteEntry.28f290402448f57ddc18.js.map
jupyter_exec-0.0.3.data/data/share/jupyter/labextensions/@datalayer/jupyter-exec/static/style.js
jupyter_exec-0.0.3.data/data/share/jupyter/labextensions/@datalayer/jupyter-exec/static/style_index_js.4b0f88f81e9fa09aca0a.js
jupyter_exec-0.0.3.data/data/share/jupyter/labextensions/@datalayer/jupyter-exec/static/style_index_js.4b0f88f81e9fa09aca0a.js.map
jupyter_exec-0.0.3.dist-info/METADATA
jupyter_exec-0.0.3.dist-info/WHEEL
jupyter_exec-0.0.3.dist-info/licenses/LICENSE
jupyter_exec-0.0.3.dist-info/RECORD
